strid/__init__.py
strid/_fdid.py
strid/_subspaceid.py
strid/spatial.py
strid/stabdiag.py
strid/utils.py
strid/tests/__init__.py
strid/tests/test_fdid.py
strid/tests/test_spatial.py
strid/tests/test_subspace.py
strid/tests/test_utils.py
strid-0.4.3.dist-info/LICENSE
strid-0.4.3.dist-info/METADATA
strid-0.4.3.dist-info/WHEEL
strid-0.4.3.dist-info/top_level.txt
strid-0.4.3.dist-info/RECORD
