Metadata-Version: 2.1
Name: strid
Version: 0.4.3
Summary: System identification of linear time-invariant systems
Home-page: https://github.com/gunnstein/strid
Author: Gunnstein T. Frøseth
Author-email: gunnstein@mailbox.org
License: ISC
Platform: UNKNOWN
Classifier: License :: OSI Approved :: ISC License (ISCL)
Classifier: Operating System :: OS Independent
Classifier: Programming Language :: Python :: 3
Classifier: Topic :: Scientific/Engineering
Requires-Python: >=3.6
License-File: LICENSE
Requires-Dist: numpy
Requires-Dist: scipy
Requires-Dist: matplotlib
